tests/__init__.py
tests/test_basic.py
waveshaping/__init__.py
waveshaping/_version.py
waveshaping/clip.py
waveshaping/fold.py
waveshaping/polynomial.py
waveshaping/rectify.py
waveshaping/saturate.py
waveshaping/special.py
waveshaping/utils.py
waveshaping_py-0.1.0.dist-info/licenses/LICENSE
waveshaping_py-0.1.0.dist-info/METADATA
waveshaping_py-0.1.0.dist-info/WHEEL
waveshaping_py-0.1.0.dist-info/top_level.txt
waveshaping_py-0.1.0.dist-info/RECORD
