Metadata-Version: 2.4
Name: waveshaping-py
Version: 0.1.0
Summary: Python library for audio waveshaping and distortion effects
Home-page: https://github.com/tsugumasa320/waveshaping-py
Author: Tsuguma Sayutani
Author-email: 
License: MIT License
Project-URL: Homepage, https://github.com/tsugumasa320/waveshaping-py
Project-URL: Bug Reports, https://github.com/tsugumasa320/waveshaping-py/issues
Project-URL: Source, https://github.com/tsugumasa320/waveshaping-py
Project-URL: Documentation, https://github.com/tsugumasa320/waveshaping-py
Keywords: audio,signal processing,waveshaping,distortion,effects,music
Classifier: Development Status :: 3 - Alpha
Classifier: Intended Audience :: Developers
Classifier: License :: OSI Approved :: MIT License
Classifier: Operating System :: OS Independent
Classifier: Programming Language :: Python :: 3
Classifier: Programming Language :: Python :: 3.7
Classifier: Programming Language :: Python :: 3.8
Classifier: Programming Language :: Python :: 3.9
Classifier: Programming Language :: Python :: 3.10
Classifier: Programming Language :: Python :: 3.11
Classifier: Topic :: Multimedia :: Sound/Audio
Classifier: Topic :: Multimedia :: Sound/Audio :: Analysis
Classifier: Topic :: Software Development :: Libraries :: Python Modules
Requires-Python: >=3.7
License-File: LICENSE
Requires-Dist: numpy>=1.19.0
Requires-Dist: scipy>=1.5.0
Provides-Extra: dev
Requires-Dist: pytest>=6.0; extra == "dev"
Requires-Dist: pytest-cov>=2.0; extra == "dev"
Requires-Dist: black>=21.0; extra == "dev"
Requires-Dist: flake8>=3.8; extra == "dev"
Requires-Dist: mypy>=0.812; extra == "dev"
Provides-Extra: examples
Requires-Dist: matplotlib>=3.3.0; extra == "examples"
Requires-Dist: soundfile>=0.10.0; extra == "examples"
Dynamic: home-page
Dynamic: license-file
Dynamic: requires-python
